mooss/__init__.py
mooss/serialize/__init__.py
mooss/serialize/__version__.py
mooss/serialize/_field_types.py
mooss/serialize/interface.py
mooss_serialize-0.0.5.dist-info/LICENSE
mooss_serialize-0.0.5.dist-info/METADATA
mooss_serialize-0.0.5.dist-info/WHEEL
mooss_serialize-0.0.5.dist-info/top_level.txt
mooss_serialize-0.0.5.dist-info/RECORD
