Metadata-Version: 2.1
Name: mooss-serialize
Version: 0.0.5
Summary: A Python package to help with serialization and deserialization of dataclasses through the help of a common interface while also insuring the parsed data is properly typed and handled in many situations.
Home-page: https://github.com/aziascreations/mooss-serialize
Author: Herwin Bozet
Author-email: herwin.bozet@gmail.com
Maintainer: Herwin Bozet
Maintainer-email: herwin.bozet@gmail.com
License: UNKNOWN
Platform: UNKNOWN
Classifier: Development Status :: 3 - Alpha
Classifier: License :: OSI Approved :: The Unlicense (Unlicense)
Classifier: Operating System :: OS Independent
Classifier: Programming Language :: Python :: 3
Classifier: Programming Language :: Python :: 3.9
Classifier: Programming Language :: Python :: 3.10
Classifier: Programming Language :: Python :: Implementation :: CPython
Classifier: Programming Language :: Python :: Implementation :: PyPy
Requires-Python: >=3.9
License-File: LICENSE
Provides-Extra: dev
Requires-Dist: nose2 (<1.0.0,>=0.11.0) ; extra == 'dev'
Requires-Dist: semver (<3.0.0,>=2.13.0) ; extra == 'dev'
Requires-Dist: check-manifest (<1.0,>=0.47) ; extra == 'dev'
